setup.py
server_monitoring/__init__.py
server_monitoring/getlogs.py
server_monitoring.egg-info/PKG-INFO
server_monitoring.egg-info/SOURCES.txt
server_monitoring.egg-info/dependency_links.txt
server_monitoring.egg-info/not-zip-safe
server_monitoring.egg-info/top_level.txt