Metadata-Version: 2.1
Name: server-monitoring
Version: 0.1
Summary: module created to monitory server performance
Home-page: UNKNOWN
Author: Derik Bortoletto
License: UNKNOWN
Platform: UNKNOWN
